[
    {
        "file": "2021MLData10.json",
        "evaluated_file": "2024MLDataToEvaluate10.json",
        "key": "MIA@NYK@2025_03_17",
        "predictions": {
            "isHomeWinner": {
                "RandomForest": {
                    "prediction": 1,
                    "probability": 0.57
                },
                "LogisticRegression": {
                    "prediction": 0,
                    "probability": 0.5723774014839086
                }
            }
        }
    },
    {
        "file": "2021MLData10.json",
        "evaluated_file": "2024MLDataToEvaluate10.json",
        "key": "CHI@UTA@2025_03_17",
        "predictions": {
            "isHomeWinner": {
                "RandomForest": {
                    "prediction": 0,
                    "probability": 0.64
                },
                "LogisticRegression": {
                    "prediction": 0,
                    "probability": 0.6181308687517975
                }
            }
        }
    },
    {
        "file": "2021MLData10.json",
        "evaluated_file": "2024MLDataToEvaluate10.json",
        "key": "IND@MIN@2025_03_17",
        "predictions": {
            "isHomeWinner": {
                "RandomForest": {
                    "prediction": 1,
                    "probability": 0.76
                },
                "LogisticRegression": {
                    "prediction": 1,
                    "probability": 0.787753295484517
                }
            }
        }
    },
    {
        "file": "2021MLData10.json",
        "evaluated_file": "2024MLDataToEvaluate10.json",
        "key": "DET@NOP@2025_03_17",
        "predictions": {
            "isHomeWinner": {
                "RandomForest": {
                    "prediction": 0,
                    "probability": 0.68
                },
                "LogisticRegression": {
                    "prediction": 0,
                    "probability": 0.8428261726960338
                }
            }
        }
    },
    {
        "file": "2021MLData10.json",
        "evaluated_file": "2024MLDataToEvaluate10.json",
        "key": "WAS@POR@2025_03_17",
        "predictions": {
            "isHomeWinner": {
                "RandomForest": {
                    "prediction": 1,
                    "probability": 0.59
                },
                "LogisticRegression": {
                    "prediction": 1,
                    "probability": 0.640889339318865
                }
            }
        }
    },
    {
        "file": "2021MLData10.json",
        "evaluated_file": "2024MLDataToEvaluate10.json",
        "key": "TOR@PHO@2025_03_17",
        "predictions": {
            "isHomeWinner": {
                "RandomForest": {
                    "prediction": 1,
                    "probability": 0.53
                },
                "LogisticRegression": {
                    "prediction": 0,
                    "probability": 0.6729936370958608
                }
            }
        }
    },
    {
        "file": "2021MLData10.json",
        "evaluated_file": "2024MLDataToEvaluate10.json",
        "key": "PHI@HOU@2025_03_17",
        "predictions": {
            "isHomeWinner": {
                "RandomForest": {
                    "prediction": 1,
                    "probability": 0.77
                },
                "LogisticRegression": {
                    "prediction": 1,
                    "probability": 0.645094871164087
                }
            }
        }
    },
    {
        "file": "2021MLData10.json",
        "evaluated_file": "2024MLDataToEvaluate10.json",
        "key": "DEN@GSW@2025_03_17",
        "predictions": {
            "isHomeWinner": {
                "RandomForest": {
                    "prediction": 1,
                    "probability": 0.71
                },
                "LogisticRegression": {
                    "prediction": 1,
                    "probability": 0.7197008065216448
                }
            }
        }
    },
    {
        "file": "2021MLData10.json",
        "evaluated_file": "2024MLDataToEvaluate10.json",
        "key": "SAS@LAL@2025_03_17",
        "predictions": {
            "isHomeWinner": {
                "RandomForest": {
                    "prediction": 0,
                    "probability": 0.53
                },
                "LogisticRegression": {
                    "prediction": 1,
                    "probability": 0.5626806801507355
                }
            }
        }
    },
    {
        "file": "2021MLData10.json",
        "evaluated_file": "2024MLDataToEvaluate10.json",
        "key": "MEM@SAC@2025_03_17",
        "predictions": {
            "isHomeWinner": {
                "RandomForest": {
                    "prediction": 1,
                    "probability": 0.6
                },
                "LogisticRegression": {
                    "prediction": 0,
                    "probability": 0.5055188692648116
                }
            }
        }
    },
    {
        "file": "2021MLData10.json",
        "evaluated_file": "2024MLDataToEvaluate10.json",
        "key": "ORL@SAS@2025_03_17",
        "predictions": {
            "isHomeWinner": {
                "RandomForest": {
                    "prediction": 1,
                    "probability": 0.53
                },
                "LogisticRegression": {
                    "prediction": 1,
                    "probability": 0.5493057012721109
                }
            }
        }
    },
    {
        "file": "2024MLData10.json",
        "evaluated_file": "2024MLDataToEvaluate10.json",
        "key": "MIA@NYK@2025_03_17",
        "predictions": {
            "isHomeWinner": {
                "RandomForest": {
                    "prediction": 1,
                    "probability": 0.69
                },
                "LogisticRegression": {
                    "prediction": 1,
                    "probability": 0.658845944427548
                }
            }
        }
    },
    {
        "file": "2024MLData10.json",
        "evaluated_file": "2024MLDataToEvaluate10.json",
        "key": "CHI@UTA@2025_03_17",
        "predictions": {
            "isHomeWinner": {
                "RandomForest": {
                    "prediction": 0,
                    "probability": 0.73
                },
                "LogisticRegression": {
                    "prediction": 0,
                    "probability": 0.7114270979400001
                }
            }
        }
    },
    {
        "file": "2024MLData10.json",
        "evaluated_file": "2024MLDataToEvaluate10.json",
        "key": "IND@MIN@2025_03_17",
        "predictions": {
            "isHomeWinner": {
                "RandomForest": {
                    "prediction": 1,
                    "probability": 0.74
                },
                "LogisticRegression": {
                    "prediction": 1,
                    "probability": 0.7620897405675054
                }
            }
        }
    },
    {
        "file": "2024MLData10.json",
        "evaluated_file": "2024MLDataToEvaluate10.json",
        "key": "DET@NOP@2025_03_17",
        "predictions": {
            "isHomeWinner": {
                "RandomForest": {
                    "prediction": 0,
                    "probability": 0.67
                },
                "LogisticRegression": {
                    "prediction": 0,
                    "probability": 0.9205289257751825
                }
            }
        }
    },
    {
        "file": "2024MLData10.json",
        "evaluated_file": "2024MLDataToEvaluate10.json",
        "key": "WAS@POR@2025_03_17",
        "predictions": {
            "isHomeWinner": {
                "RandomForest": {
                    "prediction": 0,
                    "probability": 0.5
                },
                "LogisticRegression": {
                    "prediction": 1,
                    "probability": 0.6404416626465603
                }
            }
        }
    },
    {
        "file": "2024MLData10.json",
        "evaluated_file": "2024MLDataToEvaluate10.json",
        "key": "TOR@PHO@2025_03_17",
        "predictions": {
            "isHomeWinner": {
                "RandomForest": {
                    "prediction": 1,
                    "probability": 0.55
                },
                "LogisticRegression": {
                    "prediction": 1,
                    "probability": 0.665470627310992
                }
            }
        }
    },
    {
        "file": "2024MLData10.json",
        "evaluated_file": "2024MLDataToEvaluate10.json",
        "key": "PHI@HOU@2025_03_17",
        "predictions": {
            "isHomeWinner": {
                "RandomForest": {
                    "prediction": 1,
                    "probability": 0.92
                },
                "LogisticRegression": {
                    "prediction": 1,
                    "probability": 0.9690636036460568
                }
            }
        }
    },
    {
        "file": "2024MLData10.json",
        "evaluated_file": "2024MLDataToEvaluate10.json",
        "key": "DEN@GSW@2025_03_17",
        "predictions": {
            "isHomeWinner": {
                "RandomForest": {
                    "prediction": 1,
                    "probability": 0.73
                },
                "LogisticRegression": {
                    "prediction": 1,
                    "probability": 0.9334123269082035
                }
            }
        }
    },
    {
        "file": "2024MLData10.json",
        "evaluated_file": "2024MLDataToEvaluate10.json",
        "key": "SAS@LAL@2025_03_17",
        "predictions": {
            "isHomeWinner": {
                "RandomForest": {
                    "prediction": 1,
                    "probability": 0.6
                },
                "LogisticRegression": {
                    "prediction": 1,
                    "probability": 0.9464667464890265
                }
            }
        }
    },
    {
        "file": "2024MLData10.json",
        "evaluated_file": "2024MLDataToEvaluate10.json",
        "key": "MEM@SAC@2025_03_17",
        "predictions": {
            "isHomeWinner": {
                "RandomForest": {
                    "prediction": 0,
                    "probability": 0.59
                },
                "LogisticRegression": {
                    "prediction": 0,
                    "probability": 0.5342545175604094
                }
            }
        }
    },
    {
        "file": "2024MLData10.json",
        "evaluated_file": "2024MLDataToEvaluate10.json",
        "key": "ORL@SAS@2025_03_17",
        "predictions": {
            "isHomeWinner": {
                "RandomForest": {
                    "prediction": 1,
                    "probability": 0.51
                },
                "LogisticRegression": {
                    "prediction": 1,
                    "probability": 0.5889881431275821
                }
            }
        }
    },
    {
        "file": "2022MLData10.json",
        "evaluated_file": "2024MLDataToEvaluate10.json",
        "key": "MIA@NYK@2025_03_17",
        "predictions": {
            "isHomeWinner": {
                "RandomForest": {
                    "prediction": 1,
                    "probability": 0.65
                },
                "LogisticRegression": {
                    "prediction": 1,
                    "probability": 0.6915288597237071
                }
            }
        }
    },
    {
        "file": "2022MLData10.json",
        "evaluated_file": "2024MLDataToEvaluate10.json",
        "key": "CHI@UTA@2025_03_17",
        "predictions": {
            "isHomeWinner": {
                "RandomForest": {
                    "prediction": 0,
                    "probability": 0.69
                },
                "LogisticRegression": {
                    "prediction": 0,
                    "probability": 0.834252657022047
                }
            }
        }
    },
    {
        "file": "2022MLData10.json",
        "evaluated_file": "2024MLDataToEvaluate10.json",
        "key": "IND@MIN@2025_03_17",
        "predictions": {
            "isHomeWinner": {
                "RandomForest": {
                    "prediction": 1,
                    "probability": 0.66
                },
                "LogisticRegression": {
                    "prediction": 1,
                    "probability": 0.7972674056886224
                }
            }
        }
    },
    {
        "file": "2022MLData10.json",
        "evaluated_file": "2024MLDataToEvaluate10.json",
        "key": "DET@NOP@2025_03_17",
        "predictions": {
            "isHomeWinner": {
                "RandomForest": {
                    "prediction": 0,
                    "probability": 0.62
                },
                "LogisticRegression": {
                    "prediction": 0,
                    "probability": 0.8368124876205769
                }
            }
        }
    },
    {
        "file": "2022MLData10.json",
        "evaluated_file": "2024MLDataToEvaluate10.json",
        "key": "WAS@POR@2025_03_17",
        "predictions": {
            "isHomeWinner": {
                "RandomForest": {
                    "prediction": 1,
                    "probability": 0.67
                },
                "LogisticRegression": {
                    "prediction": 1,
                    "probability": 0.5884284816665445
                }
            }
        }
    },
    {
        "file": "2022MLData10.json",
        "evaluated_file": "2024MLDataToEvaluate10.json",
        "key": "TOR@PHO@2025_03_17",
        "predictions": {
            "isHomeWinner": {
                "RandomForest": {
                    "prediction": 1,
                    "probability": 0.76
                },
                "LogisticRegression": {
                    "prediction": 1,
                    "probability": 0.8970510847461883
                }
            }
        }
    },
    {
        "file": "2022MLData10.json",
        "evaluated_file": "2024MLDataToEvaluate10.json",
        "key": "PHI@HOU@2025_03_17",
        "predictions": {
            "isHomeWinner": {
                "RandomForest": {
                    "prediction": 1,
                    "probability": 0.78
                },
                "LogisticRegression": {
                    "prediction": 1,
                    "probability": 0.9288115328199056
                }
            }
        }
    },
    {
        "file": "2022MLData10.json",
        "evaluated_file": "2024MLDataToEvaluate10.json",
        "key": "DEN@GSW@2025_03_17",
        "predictions": {
            "isHomeWinner": {
                "RandomForest": {
                    "prediction": 1,
                    "probability": 0.72
                },
                "LogisticRegression": {
                    "prediction": 1,
                    "probability": 0.9531480498305674
                }
            }
        }
    },
    {
        "file": "2022MLData10.json",
        "evaluated_file": "2024MLDataToEvaluate10.json",
        "key": "SAS@LAL@2025_03_17",
        "predictions": {
            "isHomeWinner": {
                "RandomForest": {
                    "prediction": 1,
                    "probability": 0.56
                },
                "LogisticRegression": {
                    "prediction": 1,
                    "probability": 0.5128827213296527
                }
            }
        }
    },
    {
        "file": "2022MLData10.json",
        "evaluated_file": "2024MLDataToEvaluate10.json",
        "key": "MEM@SAC@2025_03_17",
        "predictions": {
            "isHomeWinner": {
                "RandomForest": {
                    "prediction": 1,
                    "probability": 0.69
                },
                "LogisticRegression": {
                    "prediction": 1,
                    "probability": 0.7334464963107906
                }
            }
        }
    },
    {
        "file": "2022MLData10.json",
        "evaluated_file": "2024MLDataToEvaluate10.json",
        "key": "ORL@SAS@2025_03_17",
        "predictions": {
            "isHomeWinner": {
                "RandomForest": {
                    "prediction": 1,
                    "probability": 0.6
                },
                "LogisticRegression": {
                    "prediction": 1,
                    "probability": 0.5354539244818476
                }
            }
        }
    },
    {
        "file": "2016MLData10.json",
        "evaluated_file": "2024MLDataToEvaluate10.json",
        "key": "MIA@NYK@2025_03_17",
        "predictions": {
            "isHomeWinner": {
                "RandomForest": {
                    "prediction": 1,
                    "probability": 0.67
                },
                "LogisticRegression": {
                    "prediction": 1,
                    "probability": 0.8390741217240604
                }
            }
        }
    },
    {
        "file": "2016MLData10.json",
        "evaluated_file": "2024MLDataToEvaluate10.json",
        "key": "CHI@UTA@2025_03_17",
        "predictions": {
            "isHomeWinner": {
                "RandomForest": {
                    "prediction": 0,
                    "probability": 0.57
                },
                "LogisticRegression": {
                    "prediction": 0,
                    "probability": 0.7188979303696027
                }
            }
        }
    },
    {
        "file": "2016MLData10.json",
        "evaluated_file": "2024MLDataToEvaluate10.json",
        "key": "IND@MIN@2025_03_17",
        "predictions": {
            "isHomeWinner": {
                "RandomForest": {
                    "prediction": 1,
                    "probability": 0.58
                },
                "LogisticRegression": {
                    "prediction": 1,
                    "probability": 0.7396423273819076
                }
            }
        }
    },
    {
        "file": "2016MLData10.json",
        "evaluated_file": "2024MLDataToEvaluate10.json",
        "key": "DET@NOP@2025_03_17",
        "predictions": {
            "isHomeWinner": {
                "RandomForest": {
                    "prediction": 1,
                    "probability": 0.54
                },
                "LogisticRegression": {
                    "prediction": 0,
                    "probability": 0.8030058769903772
                }
            }
        }
    },
    {
        "file": "2016MLData10.json",
        "evaluated_file": "2024MLDataToEvaluate10.json",
        "key": "WAS@POR@2025_03_17",
        "predictions": {
            "isHomeWinner": {
                "RandomForest": {
                    "prediction": 1,
                    "probability": 0.59
                },
                "LogisticRegression": {
                    "prediction": 1,
                    "probability": 0.6715370009090731
                }
            }
        }
    },
    {
        "file": "2016MLData10.json",
        "evaluated_file": "2024MLDataToEvaluate10.json",
        "key": "TOR@PHO@2025_03_17",
        "predictions": {
            "isHomeWinner": {
                "RandomForest": {
                    "prediction": 1,
                    "probability": 0.57
                },
                "LogisticRegression": {
                    "prediction": 0,
                    "probability": 0.6451767793012884
                }
            }
        }
    },
    {
        "file": "2016MLData10.json",
        "evaluated_file": "2024MLDataToEvaluate10.json",
        "key": "PHI@HOU@2025_03_17",
        "predictions": {
            "isHomeWinner": {
                "RandomForest": {
                    "prediction": 1,
                    "probability": 0.73
                },
                "LogisticRegression": {
                    "prediction": 1,
                    "probability": 0.9508905048924047
                }
            }
        }
    },
    {
        "file": "2016MLData10.json",
        "evaluated_file": "2024MLDataToEvaluate10.json",
        "key": "DEN@GSW@2025_03_17",
        "predictions": {
            "isHomeWinner": {
                "RandomForest": {
                    "prediction": 1,
                    "probability": 0.52
                },
                "LogisticRegression": {
                    "prediction": 1,
                    "probability": 0.8233155115172376
                }
            }
        }
    },
    {
        "file": "2016MLData10.json",
        "evaluated_file": "2024MLDataToEvaluate10.json",
        "key": "SAS@LAL@2025_03_17",
        "predictions": {
            "isHomeWinner": {
                "RandomForest": {
                    "prediction": 0,
                    "probability": 0.51
                },
                "LogisticRegression": {
                    "prediction": 1,
                    "probability": 0.6290607029376226
                }
            }
        }
    },
    {
        "file": "2016MLData10.json",
        "evaluated_file": "2024MLDataToEvaluate10.json",
        "key": "MEM@SAC@2025_03_17",
        "predictions": {
            "isHomeWinner": {
                "RandomForest": {
                    "prediction": 1,
                    "probability": 0.54
                },
                "LogisticRegression": {
                    "prediction": 1,
                    "probability": 0.5182569006022946
                }
            }
        }
    },
    {
        "file": "2016MLData10.json",
        "evaluated_file": "2024MLDataToEvaluate10.json",
        "key": "ORL@SAS@2025_03_17",
        "predictions": {
            "isHomeWinner": {
                "RandomForest": {
                    "prediction": 1,
                    "probability": 0.64
                },
                "LogisticRegression": {
                    "prediction": 0,
                    "probability": 0.6389937701291446
                }
            }
        }
    },
    {
        "file": "2015MLData10.json",
        "evaluated_file": "2024MLDataToEvaluate10.json",
        "key": "MIA@NYK@2025_03_17",
        "predictions": {
            "isHomeWinner": {
                "RandomForest": {
                    "prediction": 1,
                    "probability": 0.71
                },
                "LogisticRegression": {
                    "prediction": 1,
                    "probability": 0.7510178583904412
                }
            }
        }
    },
    {
        "file": "2015MLData10.json",
        "evaluated_file": "2024MLDataToEvaluate10.json",
        "key": "CHI@UTA@2025_03_17",
        "predictions": {
            "isHomeWinner": {
                "RandomForest": {
                    "prediction": 0,
                    "probability": 0.64
                },
                "LogisticRegression": {
                    "prediction": 1,
                    "probability": 0.5131339089701491
                }
            }
        }
    },
    {
        "file": "2015MLData10.json",
        "evaluated_file": "2024MLDataToEvaluate10.json",
        "key": "IND@MIN@2025_03_17",
        "predictions": {
            "isHomeWinner": {
                "RandomForest": {
                    "prediction": 1,
                    "probability": 0.65
                },
                "LogisticRegression": {
                    "prediction": 1,
                    "probability": 0.9587408811332665
                }
            }
        }
    },
    {
        "file": "2015MLData10.json",
        "evaluated_file": "2024MLDataToEvaluate10.json",
        "key": "DET@NOP@2025_03_17",
        "predictions": {
            "isHomeWinner": {
                "RandomForest": {
                    "prediction": 0,
                    "probability": 0.51
                },
                "LogisticRegression": {
                    "prediction": 0,
                    "probability": 0.7383446120326631
                }
            }
        }
    },
    {
        "file": "2015MLData10.json",
        "evaluated_file": "2024MLDataToEvaluate10.json",
        "key": "WAS@POR@2025_03_17",
        "predictions": {
            "isHomeWinner": {
                "RandomForest": {
                    "prediction": 1,
                    "probability": 0.51
                },
                "LogisticRegression": {
                    "prediction": 1,
                    "probability": 0.8520057276037083
                }
            }
        }
    },
    {
        "file": "2015MLData10.json",
        "evaluated_file": "2024MLDataToEvaluate10.json",
        "key": "TOR@PHO@2025_03_17",
        "predictions": {
            "isHomeWinner": {
                "RandomForest": {
                    "prediction": 0,
                    "probability": 0.5
                },
                "LogisticRegression": {
                    "prediction": 1,
                    "probability": 0.8958495458455654
                }
            }
        }
    },
    {
        "file": "2015MLData10.json",
        "evaluated_file": "2024MLDataToEvaluate10.json",
        "key": "PHI@HOU@2025_03_17",
        "predictions": {
            "isHomeWinner": {
                "RandomForest": {
                    "prediction": 1,
                    "probability": 0.71
                },
                "LogisticRegression": {
                    "prediction": 1,
                    "probability": 0.994379407112391
                }
            }
        }
    },
    {
        "file": "2015MLData10.json",
        "evaluated_file": "2024MLDataToEvaluate10.json",
        "key": "DEN@GSW@2025_03_17",
        "predictions": {
            "isHomeWinner": {
                "RandomForest": {
                    "prediction": 1,
                    "probability": 0.52
                },
                "LogisticRegression": {
                    "prediction": 1,
                    "probability": 0.9719281877505801
                }
            }
        }
    },
    {
        "file": "2015MLData10.json",
        "evaluated_file": "2024MLDataToEvaluate10.json",
        "key": "SAS@LAL@2025_03_17",
        "predictions": {
            "isHomeWinner": {
                "RandomForest": {
                    "prediction": 1,
                    "probability": 0.54
                },
                "LogisticRegression": {
                    "prediction": 1,
                    "probability": 0.9882453465084038
                }
            }
        }
    },
    {
        "file": "2015MLData10.json",
        "evaluated_file": "2024MLDataToEvaluate10.json",
        "key": "MEM@SAC@2025_03_17",
        "predictions": {
            "isHomeWinner": {
                "RandomForest": {
                    "prediction": 1,
                    "probability": 0.54
                },
                "LogisticRegression": {
                    "prediction": 1,
                    "probability": 0.7240825429336738
                }
            }
        }
    },
    {
        "file": "2015MLData10.json",
        "evaluated_file": "2024MLDataToEvaluate10.json",
        "key": "ORL@SAS@2025_03_17",
        "predictions": {
            "isHomeWinner": {
                "RandomForest": {
                    "prediction": 1,
                    "probability": 0.62
                },
                "LogisticRegression": {
                    "prediction": 1,
                    "probability": 0.9377689385375938
                }
            }
        }
    },
    {
        "file": "2023MLData10.json",
        "evaluated_file": "2024MLDataToEvaluate10.json",
        "key": "MIA@NYK@2025_03_17",
        "predictions": {
            "isHomeWinner": {
                "RandomForest": {
                    "prediction": 1,
                    "probability": 0.68
                },
                "LogisticRegression": {
                    "prediction": 1,
                    "probability": 0.6901389992222632
                }
            }
        }
    },
    {
        "file": "2023MLData10.json",
        "evaluated_file": "2024MLDataToEvaluate10.json",
        "key": "CHI@UTA@2025_03_17",
        "predictions": {
            "isHomeWinner": {
                "RandomForest": {
                    "prediction": 0,
                    "probability": 0.68
                },
                "LogisticRegression": {
                    "prediction": 0,
                    "probability": 0.6122676442596751
                }
            }
        }
    },
    {
        "file": "2023MLData10.json",
        "evaluated_file": "2024MLDataToEvaluate10.json",
        "key": "IND@MIN@2025_03_17",
        "predictions": {
            "isHomeWinner": {
                "RandomForest": {
                    "prediction": 1,
                    "probability": 0.62
                },
                "LogisticRegression": {
                    "prediction": 0,
                    "probability": 0.5517663278700244
                }
            }
        }
    },
    {
        "file": "2023MLData10.json",
        "evaluated_file": "2024MLDataToEvaluate10.json",
        "key": "DET@NOP@2025_03_17",
        "predictions": {
            "isHomeWinner": {
                "RandomForest": {
                    "prediction": 0,
                    "probability": 0.64
                },
                "LogisticRegression": {
                    "prediction": 0,
                    "probability": 0.7123032742683848
                }
            }
        }
    },
    {
        "file": "2023MLData10.json",
        "evaluated_file": "2024MLDataToEvaluate10.json",
        "key": "WAS@POR@2025_03_17",
        "predictions": {
            "isHomeWinner": {
                "RandomForest": {
                    "prediction": 1,
                    "probability": 0.54
                },
                "LogisticRegression": {
                    "prediction": 1,
                    "probability": 0.5644749265023566
                }
            }
        }
    },
    {
        "file": "2023MLData10.json",
        "evaluated_file": "2024MLDataToEvaluate10.json",
        "key": "TOR@PHO@2025_03_17",
        "predictions": {
            "isHomeWinner": {
                "RandomForest": {
                    "prediction": 1,
                    "probability": 0.58
                },
                "LogisticRegression": {
                    "prediction": 1,
                    "probability": 0.6116703729412506
                }
            }
        }
    },
    {
        "file": "2023MLData10.json",
        "evaluated_file": "2024MLDataToEvaluate10.json",
        "key": "PHI@HOU@2025_03_17",
        "predictions": {
            "isHomeWinner": {
                "RandomForest": {
                    "prediction": 1,
                    "probability": 0.86
                },
                "LogisticRegression": {
                    "prediction": 1,
                    "probability": 0.9721703724554791
                }
            }
        }
    },
    {
        "file": "2023MLData10.json",
        "evaluated_file": "2024MLDataToEvaluate10.json",
        "key": "DEN@GSW@2025_03_17",
        "predictions": {
            "isHomeWinner": {
                "RandomForest": {
                    "prediction": 1,
                    "probability": 0.75
                },
                "LogisticRegression": {
                    "prediction": 1,
                    "probability": 0.8427668280830521
                }
            }
        }
    },
    {
        "file": "2023MLData10.json",
        "evaluated_file": "2024MLDataToEvaluate10.json",
        "key": "SAS@LAL@2025_03_17",
        "predictions": {
            "isHomeWinner": {
                "RandomForest": {
                    "prediction": 1,
                    "probability": 0.54
                },
                "LogisticRegression": {
                    "prediction": 1,
                    "probability": 0.7089971933873996
                }
            }
        }
    },
    {
        "file": "2023MLData10.json",
        "evaluated_file": "2024MLDataToEvaluate10.json",
        "key": "MEM@SAC@2025_03_17",
        "predictions": {
            "isHomeWinner": {
                "RandomForest": {
                    "prediction": 0,
                    "probability": 0.55
                },
                "LogisticRegression": {
                    "prediction": 0,
                    "probability": 0.5002858015687395
                }
            }
        }
    },
    {
        "file": "2023MLData10.json",
        "evaluated_file": "2024MLDataToEvaluate10.json",
        "key": "ORL@SAS@2025_03_17",
        "predictions": {
            "isHomeWinner": {
                "RandomForest": {
                    "prediction": 1,
                    "probability": 0.57
                },
                "LogisticRegression": {
                    "prediction": 1,
                    "probability": 0.5634282387407464
                }
            }
        }
    },
    {
        "file": "2018MLData10.json",
        "evaluated_file": "2024MLDataToEvaluate10.json",
        "key": "MIA@NYK@2025_03_17",
        "predictions": {
            "isHomeWinner": {
                "RandomForest": {
                    "prediction": 1,
                    "probability": 0.69
                },
                "LogisticRegression": {
                    "prediction": 1,
                    "probability": 0.6882610233370193
                }
            }
        }
    },
    {
        "file": "2018MLData10.json",
        "evaluated_file": "2024MLDataToEvaluate10.json",
        "key": "CHI@UTA@2025_03_17",
        "predictions": {
            "isHomeWinner": {
                "RandomForest": {
                    "prediction": 0,
                    "probability": 0.58
                },
                "LogisticRegression": {
                    "prediction": 0,
                    "probability": 0.8072041772760711
                }
            }
        }
    },
    {
        "file": "2018MLData10.json",
        "evaluated_file": "2024MLDataToEvaluate10.json",
        "key": "IND@MIN@2025_03_17",
        "predictions": {
            "isHomeWinner": {
                "RandomForest": {
                    "prediction": 1,
                    "probability": 0.73
                },
                "LogisticRegression": {
                    "prediction": 1,
                    "probability": 0.9678081100485065
                }
            }
        }
    },
    {
        "file": "2018MLData10.json",
        "evaluated_file": "2024MLDataToEvaluate10.json",
        "key": "DET@NOP@2025_03_17",
        "predictions": {
            "isHomeWinner": {
                "RandomForest": {
                    "prediction": 0,
                    "probability": 0.63
                },
                "LogisticRegression": {
                    "prediction": 0,
                    "probability": 0.8137620427905591
                }
            }
        }
    },
    {
        "file": "2018MLData10.json",
        "evaluated_file": "2024MLDataToEvaluate10.json",
        "key": "WAS@POR@2025_03_17",
        "predictions": {
            "isHomeWinner": {
                "RandomForest": {
                    "prediction": 1,
                    "probability": 0.72
                },
                "LogisticRegression": {
                    "prediction": 1,
                    "probability": 0.8811238837106897
                }
            }
        }
    },
    {
        "file": "2018MLData10.json",
        "evaluated_file": "2024MLDataToEvaluate10.json",
        "key": "TOR@PHO@2025_03_17",
        "predictions": {
            "isHomeWinner": {
                "RandomForest": {
                    "prediction": 0,
                    "probability": 0.54
                },
                "LogisticRegression": {
                    "prediction": 0,
                    "probability": 0.6960920992575508
                }
            }
        }
    },
    {
        "file": "2018MLData10.json",
        "evaluated_file": "2024MLDataToEvaluate10.json",
        "key": "PHI@HOU@2025_03_17",
        "predictions": {
            "isHomeWinner": {
                "RandomForest": {
                    "prediction": 1,
                    "probability": 0.9
                },
                "LogisticRegression": {
                    "prediction": 1,
                    "probability": 0.8671999135571576
                }
            }
        }
    },
    {
        "file": "2018MLData10.json",
        "evaluated_file": "2024MLDataToEvaluate10.json",
        "key": "DEN@GSW@2025_03_17",
        "predictions": {
            "isHomeWinner": {
                "RandomForest": {
                    "prediction": 1,
                    "probability": 0.8
                },
                "LogisticRegression": {
                    "prediction": 1,
                    "probability": 0.9223244995184903
                }
            }
        }
    },
    {
        "file": "2018MLData10.json",
        "evaluated_file": "2024MLDataToEvaluate10.json",
        "key": "SAS@LAL@2025_03_17",
        "predictions": {
            "isHomeWinner": {
                "RandomForest": {
                    "prediction": 1,
                    "probability": 0.6
                },
                "LogisticRegression": {
                    "prediction": 1,
                    "probability": 0.8770897335502339
                }
            }
        }
    },
    {
        "file": "2018MLData10.json",
        "evaluated_file": "2024MLDataToEvaluate10.json",
        "key": "MEM@SAC@2025_03_17",
        "predictions": {
            "isHomeWinner": {
                "RandomForest": {
                    "prediction": 1,
                    "probability": 0.7
                },
                "LogisticRegression": {
                    "prediction": 1,
                    "probability": 0.821648048952665
                }
            }
        }
    },
    {
        "file": "2018MLData10.json",
        "evaluated_file": "2024MLDataToEvaluate10.json",
        "key": "ORL@SAS@2025_03_17",
        "predictions": {
            "isHomeWinner": {
                "RandomForest": {
                    "prediction": 1,
                    "probability": 0.58
                },
                "LogisticRegression": {
                    "prediction": 1,
                    "probability": 0.6015252731974218
                }
            }
        }
    },
    {
        "file": "2019MLData10.json",
        "evaluated_file": "2024MLDataToEvaluate10.json",
        "key": "MIA@NYK@2025_03_17",
        "predictions": {
            "isHomeWinner": {
                "RandomForest": {
                    "prediction": 1,
                    "probability": 0.76
                },
                "LogisticRegression": {
                    "prediction": 1,
                    "probability": 0.8026548869627986
                }
            }
        }
    },
    {
        "file": "2019MLData10.json",
        "evaluated_file": "2024MLDataToEvaluate10.json",
        "key": "CHI@UTA@2025_03_17",
        "predictions": {
            "isHomeWinner": {
                "RandomForest": {
                    "prediction": 0,
                    "probability": 0.72
                },
                "LogisticRegression": {
                    "prediction": 0,
                    "probability": 0.8697259818708842
                }
            }
        }
    },
    {
        "file": "2019MLData10.json",
        "evaluated_file": "2024MLDataToEvaluate10.json",
        "key": "IND@MIN@2025_03_17",
        "predictions": {
            "isHomeWinner": {
                "RandomForest": {
                    "prediction": 1,
                    "probability": 0.62
                },
                "LogisticRegression": {
                    "prediction": 1,
                    "probability": 0.5569269950268038
                }
            }
        }
    },
    {
        "file": "2019MLData10.json",
        "evaluated_file": "2024MLDataToEvaluate10.json",
        "key": "DET@NOP@2025_03_17",
        "predictions": {
            "isHomeWinner": {
                "RandomForest": {
                    "prediction": 0,
                    "probability": 0.64
                },
                "LogisticRegression": {
                    "prediction": 0,
                    "probability": 0.9012112968081711
                }
            }
        }
    },
    {
        "file": "2019MLData10.json",
        "evaluated_file": "2024MLDataToEvaluate10.json",
        "key": "WAS@POR@2025_03_17",
        "predictions": {
            "isHomeWinner": {
                "RandomForest": {
                    "prediction": 1,
                    "probability": 0.59
                },
                "LogisticRegression": {
                    "prediction": 1,
                    "probability": 0.6990059331841983
                }
            }
        }
    },
    {
        "file": "2019MLData10.json",
        "evaluated_file": "2024MLDataToEvaluate10.json",
        "key": "TOR@PHO@2025_03_17",
        "predictions": {
            "isHomeWinner": {
                "RandomForest": {
                    "prediction": 1,
                    "probability": 0.57
                },
                "LogisticRegression": {
                    "prediction": 0,
                    "probability": 0.746042505046864
                }
            }
        }
    },
    {
        "file": "2019MLData10.json",
        "evaluated_file": "2024MLDataToEvaluate10.json",
        "key": "PHI@HOU@2025_03_17",
        "predictions": {
            "isHomeWinner": {
                "RandomForest": {
                    "prediction": 1,
                    "probability": 0.84
                },
                "LogisticRegression": {
                    "prediction": 1,
                    "probability": 0.9762782605405155
                }
            }
        }
    },
    {
        "file": "2019MLData10.json",
        "evaluated_file": "2024MLDataToEvaluate10.json",
        "key": "DEN@GSW@2025_03_17",
        "predictions": {
            "isHomeWinner": {
                "RandomForest": {
                    "prediction": 1,
                    "probability": 0.62
                },
                "LogisticRegression": {
                    "prediction": 1,
                    "probability": 0.9119243791698607
                }
            }
        }
    },
    {
        "file": "2019MLData10.json",
        "evaluated_file": "2024MLDataToEvaluate10.json",
        "key": "SAS@LAL@2025_03_17",
        "predictions": {
            "isHomeWinner": {
                "RandomForest": {
                    "prediction": 1,
                    "probability": 0.55
                },
                "LogisticRegression": {
                    "prediction": 0,
                    "probability": 0.5049920863955365
                }
            }
        }
    },
    {
        "file": "2019MLData10.json",
        "evaluated_file": "2024MLDataToEvaluate10.json",
        "key": "MEM@SAC@2025_03_17",
        "predictions": {
            "isHomeWinner": {
                "RandomForest": {
                    "prediction": 0,
                    "probability": 0.5
                },
                "LogisticRegression": {
                    "prediction": 0,
                    "probability": 0.5063275555458521
                }
            }
        }
    },
    {
        "file": "2019MLData10.json",
        "evaluated_file": "2024MLDataToEvaluate10.json",
        "key": "ORL@SAS@2025_03_17",
        "predictions": {
            "isHomeWinner": {
                "RandomForest": {
                    "prediction": 1,
                    "probability": 0.68
                },
                "LogisticRegression": {
                    "prediction": 1,
                    "probability": 0.6089356735160116
                }
            }
        }
    },
    {
        "file": "2017MLData10.json",
        "evaluated_file": "2024MLDataToEvaluate10.json",
        "key": "MIA@NYK@2025_03_17",
        "predictions": {
            "isHomeWinner": {
                "RandomForest": {
                    "prediction": 1,
                    "probability": 0.81
                },
                "LogisticRegression": {
                    "prediction": 1,
                    "probability": 0.7833139840011617
                }
            }
        }
    },
    {
        "file": "2017MLData10.json",
        "evaluated_file": "2024MLDataToEvaluate10.json",
        "key": "CHI@UTA@2025_03_17",
        "predictions": {
            "isHomeWinner": {
                "RandomForest": {
                    "prediction": 0,
                    "probability": 0.53
                },
                "LogisticRegression": {
                    "prediction": 0,
                    "probability": 0.9491661779254146
                }
            }
        }
    },
    {
        "file": "2017MLData10.json",
        "evaluated_file": "2024MLDataToEvaluate10.json",
        "key": "IND@MIN@2025_03_17",
        "predictions": {
            "isHomeWinner": {
                "RandomForest": {
                    "prediction": 1,
                    "probability": 0.55
                },
                "LogisticRegression": {
                    "prediction": 1,
                    "probability": 0.7487159967864824
                }
            }
        }
    },
    {
        "file": "2017MLData10.json",
        "evaluated_file": "2024MLDataToEvaluate10.json",
        "key": "DET@NOP@2025_03_17",
        "predictions": {
            "isHomeWinner": {
                "RandomForest": {
                    "prediction": 0,
                    "probability": 0.6
                },
                "LogisticRegression": {
                    "prediction": 0,
                    "probability": 0.7199392012106811
                }
            }
        }
    },
    {
        "file": "2017MLData10.json",
        "evaluated_file": "2024MLDataToEvaluate10.json",
        "key": "WAS@POR@2025_03_17",
        "predictions": {
            "isHomeWinner": {
                "RandomForest": {
                    "prediction": 1,
                    "probability": 0.58
                },
                "LogisticRegression": {
                    "prediction": 0,
                    "probability": 0.6130444766678772
                }
            }
        }
    },
    {
        "file": "2017MLData10.json",
        "evaluated_file": "2024MLDataToEvaluate10.json",
        "key": "TOR@PHO@2025_03_17",
        "predictions": {
            "isHomeWinner": {
                "RandomForest": {
                    "prediction": 0,
                    "probability": 0.55
                },
                "LogisticRegression": {
                    "prediction": 1,
                    "probability": 0.6554006690856103
                }
            }
        }
    },
    {
        "file": "2017MLData10.json",
        "evaluated_file": "2024MLDataToEvaluate10.json",
        "key": "PHI@HOU@2025_03_17",
        "predictions": {
            "isHomeWinner": {
                "RandomForest": {
                    "prediction": 1,
                    "probability": 0.61
                },
                "LogisticRegression": {
                    "prediction": 1,
                    "probability": 0.9280007450134637
                }
            }
        }
    },
    {
        "file": "2017MLData10.json",
        "evaluated_file": "2024MLDataToEvaluate10.json",
        "key": "DEN@GSW@2025_03_17",
        "predictions": {
            "isHomeWinner": {
                "RandomForest": {
                    "prediction": 0,
                    "probability": 0.55
                },
                "LogisticRegression": {
                    "prediction": 1,
                    "probability": 0.9221466113344972
                }
            }
        }
    },
    {
        "file": "2017MLData10.json",
        "evaluated_file": "2024MLDataToEvaluate10.json",
        "key": "SAS@LAL@2025_03_17",
        "predictions": {
            "isHomeWinner": {
                "RandomForest": {
                    "prediction": 0,
                    "probability": 0.58
                },
                "LogisticRegression": {
                    "prediction": 1,
                    "probability": 0.9397661666523724
                }
            }
        }
    },
    {
        "file": "2017MLData10.json",
        "evaluated_file": "2024MLDataToEvaluate10.json",
        "key": "MEM@SAC@2025_03_17",
        "predictions": {
            "isHomeWinner": {
                "RandomForest": {
                    "prediction": 0,
                    "probability": 0.62
                },
                "LogisticRegression": {
                    "prediction": 1,
                    "probability": 0.7253468639455346
                }
            }
        }
    },
    {
        "file": "2017MLData10.json",
        "evaluated_file": "2024MLDataToEvaluate10.json",
        "key": "ORL@SAS@2025_03_17",
        "predictions": {
            "isHomeWinner": {
                "RandomForest": {
                    "prediction": 1,
                    "probability": 0.64
                },
                "LogisticRegression": {
                    "prediction": 1,
                    "probability": 0.9082576695709176
                }
            }
        }
    },
    {
        "file": "2020MLData10.json",
        "evaluated_file": "2024MLDataToEvaluate10.json",
        "key": "MIA@NYK@2025_03_17",
        "predictions": {
            "isHomeWinner": {
                "RandomForest": {
                    "prediction": 1,
                    "probability": 0.76
                },
                "LogisticRegression": {
                    "prediction": 1,
                    "probability": 0.8110461324156933
                }
            }
        }
    },
    {
        "file": "2020MLData10.json",
        "evaluated_file": "2024MLDataToEvaluate10.json",
        "key": "CHI@UTA@2025_03_17",
        "predictions": {
            "isHomeWinner": {
                "RandomForest": {
                    "prediction": 0,
                    "probability": 0.65
                },
                "LogisticRegression": {
                    "prediction": 0,
                    "probability": 0.7113082632364338
                }
            }
        }
    },
    {
        "file": "2020MLData10.json",
        "evaluated_file": "2024MLDataToEvaluate10.json",
        "key": "IND@MIN@2025_03_17",
        "predictions": {
            "isHomeWinner": {
                "RandomForest": {
                    "prediction": 0,
                    "probability": 0.52
                },
                "LogisticRegression": {
                    "prediction": 1,
                    "probability": 0.7592207316938486
                }
            }
        }
    },
    {
        "file": "2020MLData10.json",
        "evaluated_file": "2024MLDataToEvaluate10.json",
        "key": "DET@NOP@2025_03_17",
        "predictions": {
            "isHomeWinner": {
                "RandomForest": {
                    "prediction": 0,
                    "probability": 0.58
                },
                "LogisticRegression": {
                    "prediction": 0,
                    "probability": 0.7375848765124583
                }
            }
        }
    },
    {
        "file": "2020MLData10.json",
        "evaluated_file": "2024MLDataToEvaluate10.json",
        "key": "WAS@POR@2025_03_17",
        "predictions": {
            "isHomeWinner": {
                "RandomForest": {
                    "prediction": 1,
                    "probability": 0.67
                },
                "LogisticRegression": {
                    "prediction": 1,
                    "probability": 0.7564038086498971
                }
            }
        }
    },
    {
        "file": "2020MLData10.json",
        "evaluated_file": "2024MLDataToEvaluate10.json",
        "key": "TOR@PHO@2025_03_17",
        "predictions": {
            "isHomeWinner": {
                "RandomForest": {
                    "prediction": 1,
                    "probability": 0.75
                },
                "LogisticRegression": {
                    "prediction": 1,
                    "probability": 0.7969951631671868
                }
            }
        }
    },
    {
        "file": "2020MLData10.json",
        "evaluated_file": "2024MLDataToEvaluate10.json",
        "key": "PHI@HOU@2025_03_17",
        "predictions": {
            "isHomeWinner": {
                "RandomForest": {
                    "prediction": 1,
                    "probability": 0.74
                },
                "LogisticRegression": {
                    "prediction": 1,
                    "probability": 0.8323827773397704
                }
            }
        }
    },
    {
        "file": "2020MLData10.json",
        "evaluated_file": "2024MLDataToEvaluate10.json",
        "key": "DEN@GSW@2025_03_17",
        "predictions": {
            "isHomeWinner": {
                "RandomForest": {
                    "prediction": 1,
                    "probability": 0.69
                },
                "LogisticRegression": {
                    "prediction": 1,
                    "probability": 0.9078243447450365
                }
            }
        }
    },
    {
        "file": "2020MLData10.json",
        "evaluated_file": "2024MLDataToEvaluate10.json",
        "key": "SAS@LAL@2025_03_17",
        "predictions": {
            "isHomeWinner": {
                "RandomForest": {
                    "prediction": 1,
                    "probability": 0.58
                },
                "LogisticRegression": {
                    "prediction": 0,
                    "probability": 0.5395739487034595
                }
            }
        }
    },
    {
        "file": "2020MLData10.json",
        "evaluated_file": "2024MLDataToEvaluate10.json",
        "key": "MEM@SAC@2025_03_17",
        "predictions": {
            "isHomeWinner": {
                "RandomForest": {
                    "prediction": 1,
                    "probability": 0.63
                },
                "LogisticRegression": {
                    "prediction": 0,
                    "probability": 0.7306893070700663
                }
            }
        }
    },
    {
        "file": "2020MLData10.json",
        "evaluated_file": "2024MLDataToEvaluate10.json",
        "key": "ORL@SAS@2025_03_17",
        "predictions": {
            "isHomeWinner": {
                "RandomForest": {
                    "prediction": 1,
                    "probability": 0.68
                },
                "LogisticRegression": {
                    "prediction": 1,
                    "probability": 0.6375722080708037
                }
            }
        }
    },
    {
        "file": "MLData10.json",
        "evaluated_file": "2024MLDataToEvaluate10.json",
        "key": "MIA@NYK@2025_03_17",
        "predictions": {
            "isHomeWinner": {
                "RandomForest": {
                    "prediction": 1,
                    "probability": 0.64
                },
                "LogisticRegression": {
                    "prediction": 1,
                    "probability": 0.6979884687643951
                }
            }
        }
    },
    {
        "file": "MLData10.json",
        "evaluated_file": "2024MLDataToEvaluate10.json",
        "key": "CHI@UTA@2025_03_17",
        "predictions": {
            "isHomeWinner": {
                "RandomForest": {
                    "prediction": 0,
                    "probability": 0.65
                },
                "LogisticRegression": {
                    "prediction": 0,
                    "probability": 0.8161516558065317
                }
            }
        }
    },
    {
        "file": "MLData10.json",
        "evaluated_file": "2024MLDataToEvaluate10.json",
        "key": "IND@MIN@2025_03_17",
        "predictions": {
            "isHomeWinner": {
                "RandomForest": {
                    "prediction": 1,
                    "probability": 0.63
                },
                "LogisticRegression": {
                    "prediction": 1,
                    "probability": 0.8204838314325292
                }
            }
        }
    },
    {
        "file": "MLData10.json",
        "evaluated_file": "2024MLDataToEvaluate10.json",
        "key": "DET@NOP@2025_03_17",
        "predictions": {
            "isHomeWinner": {
                "RandomForest": {
                    "prediction": 0,
                    "probability": 0.6
                },
                "LogisticRegression": {
                    "prediction": 0,
                    "probability": 0.7988971138806462
                }
            }
        }
    },
    {
        "file": "MLData10.json",
        "evaluated_file": "2024MLDataToEvaluate10.json",
        "key": "WAS@POR@2025_03_17",
        "predictions": {
            "isHomeWinner": {
                "RandomForest": {
                    "prediction": 1,
                    "probability": 0.65
                },
                "LogisticRegression": {
                    "prediction": 1,
                    "probability": 0.733528488577346
                }
            }
        }
    },
    {
        "file": "MLData10.json",
        "evaluated_file": "2024MLDataToEvaluate10.json",
        "key": "TOR@PHO@2025_03_17",
        "predictions": {
            "isHomeWinner": {
                "RandomForest": {
                    "prediction": 1,
                    "probability": 0.67
                },
                "LogisticRegression": {
                    "prediction": 0,
                    "probability": 0.5144812460031651
                }
            }
        }
    },
    {
        "file": "MLData10.json",
        "evaluated_file": "2024MLDataToEvaluate10.json",
        "key": "PHI@HOU@2025_03_17",
        "predictions": {
            "isHomeWinner": {
                "RandomForest": {
                    "prediction": 1,
                    "probability": 0.83
                },
                "LogisticRegression": {
                    "prediction": 1,
                    "probability": 0.9219310650606792
                }
            }
        }
    },
    {
        "file": "MLData10.json",
        "evaluated_file": "2024MLDataToEvaluate10.json",
        "key": "DEN@GSW@2025_03_17",
        "predictions": {
            "isHomeWinner": {
                "RandomForest": {
                    "prediction": 1,
                    "probability": 0.73
                },
                "LogisticRegression": {
                    "prediction": 1,
                    "probability": 0.8899662834707067
                }
            }
        }
    },
    {
        "file": "MLData10.json",
        "evaluated_file": "2024MLDataToEvaluate10.json",
        "key": "SAS@LAL@2025_03_17",
        "predictions": {
            "isHomeWinner": {
                "RandomForest": {
                    "prediction": 1,
                    "probability": 0.65
                },
                "LogisticRegression": {
                    "prediction": 1,
                    "probability": 0.8039652254216563
                }
            }
        }
    },
    {
        "file": "MLData10.json",
        "evaluated_file": "2024MLDataToEvaluate10.json",
        "key": "MEM@SAC@2025_03_17",
        "predictions": {
            "isHomeWinner": {
                "RandomForest": {
                    "prediction": 1,
                    "probability": 0.57
                },
                "LogisticRegression": {
                    "prediction": 1,
                    "probability": 0.5736789376020506
                }
            }
        }
    },
    {
        "file": "MLData10.json",
        "evaluated_file": "2024MLDataToEvaluate10.json",
        "key": "ORL@SAS@2025_03_17",
        "predictions": {
            "isHomeWinner": {
                "RandomForest": {
                    "prediction": 1,
                    "probability": 0.6
                },
                "LogisticRegression": {
                    "prediction": 1,
                    "probability": 0.6573352547672764
                }
            }
        }
    }
]